Metadata-Version: 2.1
Name: CommunityNet
Version: 1.0.0
Summary: Hierarchical GNN for graphs with community structure
Home-page: https://github.com/shobrook/CommunityNet
Author: shobrook
Author-email: shobrookj@gmail.com
License: MIT
Keywords: graph-neural-network,gnn,community,graph,graph-convolution,hierarchical
Platform: UNKNOWN
Requires-Python: >=3
